<?xml version="1.0" encoding="UTF-8" ?>
<templates>
  <t t-name="BHHrAttendanceMyMainMenu">
        <div class="o_hr_attendance_kiosk_mode_container o_home_menu_background">
            <span class="o_hr_attendance_kiosk_backdrop"/>
            <div class="o_hr_attendance_clock text-center"/>
            <div class="o_hr_attendance_kiosk_mode">
                <t t-set="checked_in" t-value="widget.employee.attendance_state=='checked_in'"/>
                <t t-if="widget.employee">
                    <div class="o_hr_attendance_user_badge o_home_menu_background">
                        <img class="img rounded-circle" t-attf-src="/web/image?model=hr.employee.public&amp;field=avatar_128&amp;id=#{widget.employee.id}" t-att-title="widget.employee.name" t-att-alt="widget.employee.name"/>
                    </div>
                    <h1 class="mb8"><t t-esc="widget.employee.name"/></h1>
                    <h3 class="mt8 mb24">
                        <t t-if="!checked_in">Welcome!</t>
                        <t t-else="">Want to check out?</t>
                    </h3>
<!--                    <t t-if="widget.attendance_location and !checked_in">-->
<!--                        <div class="form-group">-->
<!--                            <select class="form-control" id="locationSelected">-->
<!--                              <t t-foreach="widget.attendance_location" t-as="location">-->
<!--                                  <option t-att-value="location.id"><t t-esc="location.name"/></option>-->
<!--                              </t>>-->
<!--                            </select>-->
<!--                        </div>-->
<!--                    </t>-->

                    <h4 class="mt0 mb0 text-muted" t-if="checked_in">Today's work hours: <span t-esc="widget.hours_today"/></h4>
                    <a class="fa fa-7x o_hr_attendance_sign_in_out_icon fa-sign-out btn-warning" t-if="checked_in" aria-label="Sign out" title="Sign out"/>
                    <t t-if="widget.attendance_location">
                        <div class="row">
                            <t t-if="!checked_in">
                                <t t-foreach="widget.attendance_location" t-as="location">
                                    <div class="col-md-4">
                                        <a t-att-class="'fa fa-5x o_hr_attendance_sign_in_out_icon btn-secondary ' + location.loc_class_name" t-att-location-id="location.id" t-if="!checked_in" aria-label="Sign in" title="Sign in"/>
                                        <h3 class="mt0 mb0 text-muted"><b>Check in at <t t-esc="location.name"/><i class="fa fa-home" aria-hidden="true"></i></b></h3>
                                    </div>
                                </t>
                            </t>
                            <t t-else="">
                                <h3 class="col-md-12 mt0 mb0 text-muted">Click to <b t-if="checked_in">check out</b></h3>
                            </t>
                        </div>
                    </t>
                    <t t-else="">
                        <a class="fa fa-7x o_hr_attendance_sign_in_out_icon fa-sign-in btn-secondary" t-if="!checked_in" aria-label="Sign in" title="Sign in"/>
                        <h3 class="mt0 mb0 text-muted">Click to <b t-if="checked_in">check out</b><b t-if="!checked_in">check in</b></h3>
                    </t>

                </t>
                <t t-else="">
                    Warning : Your user should be linked to an employee to use attendance. Please contact your administrator.
                </t>
            </div>
        </div>
    </t>
</templates>